vonage_network/__init__.py
vonage_network/_version.py
vonage_network/vonage_network.py
vonage_network-0.1.1b0.dist-info/METADATA
vonage_network-0.1.1b0.dist-info/WHEEL
vonage_network-0.1.1b0.dist-info/top_level.txt
vonage_network-0.1.1b0.dist-info/RECORD
