Metadata-Version: 2.1
Name: vonage-network
Version: 0.1.1b0
Summary: Python Server SDK for using Vonage Network APIs
Author-email: Vonage <devrel@vonage.com>
Project-URL: homepage, https://github.com/Vonage/vonage-python-sdk
Classifier: Programming Language :: Python
Classifier: Programming Language :: Python :: 3
Classifier: Programming Language :: Python :: 3.8
Classifier: Programming Language :: Python :: 3.9
Classifier: Programming Language :: Python :: 3.10
Classifier: Programming Language :: Python :: 3.11
Classifier: Programming Language :: Python :: 3.12
Classifier: License :: OSI Approved :: Apache Software License
Requires-Python: >=3.8
Requires-Dist: vonage-utils>=1.1.2
Requires-Dist: vonage-http-client>=1.4.0
Requires-Dist: vonage-network-auth>=0.1.0b0
Requires-Dist: vonage-network-sim-swap>=0.1.0b0
